{
  "routes": [
    {
      "method": "GET",
      "path": "/unites",
      "handler": "unite.find",
      "config": {
        "policies": []
      }
    },
    {
      "method": "GET",
      "path": "/unites/count",
      "handler": "unite.count",
      "config": {
        "policies": []
      }
    },
    {
      "method": "GET",
      "path": "/unites/:id",
      "handler": "unite.findOne",
      "config": {
        "policies": []
      }
    },
    {
      "method": "POST",
      "path": "/unites",
      "handler": "unite.create",
      "config": {
        "policies": []
      }
    },
    {
      "method": "PUT",
      "path": "/unites/:id",
      "handler": "unite.update",
      "config": {
        "policies": []
      }
    },
    {
      "method": "DELETE",
      "path": "/unites/:id",
      "handler": "unite.delete",
      "config": {
        "policies": []
      }
    }
  ]
}
